FEEL/Demo_case.py
FEEL/Feel_extraction.py
FEEL/Feel_transformation.py
FEEL/__init__.py
IFEEL/Demo.py
IFEEL/Demo_case.py
IFEEL/__init__.py
IFEEL/ifeel_extraction.py
IFEEL/ifeel_transformation.py
ifeel-1.5.1.dist-info/LICENSE
ifeel-1.5.1.dist-info/METADATA
ifeel-1.5.1.dist-info/WHEEL
ifeel-1.5.1.dist-info/top_level.txt
ifeel-1.5.1.dist-info/RECORD
