Metadata-Version: 2.1
Name: ifeel
Version: 1.5.1
Summary: A python package for Interpretable Feature Extraction of Electricity Loads (IFEEL)
Home-page: https://github.com/chacehoo/IFEEL
Author: Maomao Hu
Author-email: maomao.hu@eng.ox.ac.uk
License: UNKNOWN
Platform: UNKNOWN
Classifier: Programming Language :: Python :: 3
Classifier: License :: OSI Approved :: MIT License
Classifier: Operating System :: OS Independent
Requires-Python: >=3.7
